asker/__init__.py
asker/ask.py
asker/config.py
asker/favs.py
asker/history.py
asker/llm.py
quick_asker-0.2.0.dist-info/METADATA
quick_asker-0.2.0.dist-info/WHEEL
quick_asker-0.2.0.dist-info/entry_points.txt
quick_asker-0.2.0.dist-info/top_level.txt
quick_asker-0.2.0.dist-info/RECORD
