Metadata-Version: 2.1
Name: quick-asker
Version: 0.2.0
Summary: A CLI tool for getting quick answers to programming questions
Home-page: https://github.com/BenyaminDamircheli/Asker
Author: Benyamin Damircheli
Classifier: Programming Language :: Python :: 3
Classifier: License :: OSI Approved :: MIT License
Classifier: Operating System :: OS Independent
Requires-Python: >=3.6
